mfa_problem_matrices.cp36-win_amd64.pyd
MFAProblem-0.9.0.data/scripts/install_mfa_problem_notebook.py
MFAProblem-0.9.0.data/scripts/run_create_empty_ter.py
MFAProblem-0.9.0.data/scripts/run_import_excel_data_in_data_base.py
MFAProblem-0.9.0.data/scripts/run_import_excel_proxy_in_data_base.py
MFAProblem-0.9.0.data/scripts/run_mfa_problem_check_input.py
MFAProblem-0.9.0.data/scripts/run_mfa_problem_main_with_excel.py
MFAProblem-0.9.0.data/scripts/run_proxycalc.py
mfa_problem/__init__.py
mfa_problem/io_bdd.py
mfa_problem/io_excel.py
mfa_problem/mfa_problem_check_io.py
mfa_problem/mfa_problem_format_io.py
mfa_problem/mfa_problem_main.py
mfa_problem/mfa_problem_solver.py
mfa_problem/su_trace.py
mfa_problem/tests/integration/__init__.py
mfa_problem/tests/integration/test_mfa_problem.py
mfa_problem/tests/unit/__init__.py
mfa_problem/tests/unit/test_mfa_problem_check_constraint.py
mfa_problem/tests/unit/test_mfa_problem_format_io.py
mfa_problem/tests/unit/test_mfa_problem_matrices_pybind.py
mfa_problem/tests/unit/test_mfa_problem_misc.py
MFAProblem-0.9.0.dist-info/LICENSE
MFAProblem-0.9.0.dist-info/METADATA
MFAProblem-0.9.0.dist-info/WHEEL
MFAProblem-0.9.0.dist-info/top_level.txt
MFAProblem-0.9.0.dist-info/RECORD
