Metadata-Version: 2.1
Name: MFAProblem
Version: 0.9.0
Summary: Material Flow Analysis Problem
Home-page: https://gitlab.com/su-model/mfa_problem
Author: AFM Filieres
Author-email: julien.alapetite@gmail.com
License: UNKNOWN
Platform: UNKNOWN
Requires-Dist: openpyxl
Requires-Dist: pandas
Requires-Dist: sympy
Requires-Dist: cvxpy
Requires-Dist: argparse
Requires-Dist: pybind11
Requires-Dist: xmltodict
Requires-Dist: psutil
Requires-Dist: sqlalchemy
Requires-Dist: xlrd
Requires-Dist: parameterized
Requires-Dist: numpy
